Metadata-Version: 1.0
Name: celebrity-births-test34324253252
Version: 0.0.1
Summary: Mock package that allows you to find celebrity by date of birth
Home-page: https://github.com/BlairMar/Celebs-births.git
Author: Ivan Ying
Author-email: UNKNOWN
License: MIT
Platform: UNKNOWN
